mdit_py_hugo/__init__.py
mdit_py_hugo/_shortcode_parsing.py
mdit_py_hugo/attribute.py
mdit_py_hugo/shortcode.py
mdit_py_hugo-0.3.0.dist-info/LICENSES/AGPL-3.0-or-later.txt
mdit_py_hugo-0.3.0.dist-info/LICENSES/CC-BY-SA-4.0.txt
mdit_py_hugo-0.3.0.dist-info/LICENSES/CC0-1.0.txt
mdit_py_hugo-0.3.0.dist-info/METADATA
mdit_py_hugo-0.3.0.dist-info/WHEEL
mdit_py_hugo-0.3.0.dist-info/RECORD
